Metadata-Version: 1.0
Name: django-website-coverpage
Version: 0.0.14
Summary: Easy website coverpages for Django
Home-page: https://github.com/joncombe/django-website-coverpage
Author: Jon Combe
Author-email: pypi@joncombe.net
License: BSD licence, see LICENCE file
Platform: UNKNOWN
